fast_grpc/__init__.py
fast_grpc/app.py
fast_grpc/enums.py
fast_grpc/middleware.py
fast_grpc/proto/__init__.py
fast_grpc/proto/enums.py
fast_grpc/proto/models.py
fast_grpc/proto/parse.py
fast_grpc/proto/templates/service.proto
fast_grpc/proto/utils.py
fast_grpc/service.py
py_fast_grpc-1.0.0.dist-info/METADATA
py_fast_grpc-1.0.0.dist-info/WHEEL
py_fast_grpc-1.0.0.dist-info/RECORD
