Metadata-Version: 2.3
Name: py-fast-grpc
Version: 1.0.0
Summary: gRPC simple and easy to use Python framework
License: MIT
Author: Oleg Yurchik
Requires-Python: >=3.11,<4.0
Classifier: License :: OSI Approved :: MIT License
Classifier: Programming Language :: Python :: 3
Classifier: Programming Language :: Python :: 3.11
Classifier: Programming Language :: Python :: 3.12
Classifier: Programming Language :: Python :: 3.13
Requires-Dist: grpcio (>=1.59.3,<2.0.0)
Requires-Dist: grpcio-reflection (>=1.59.3,<2.0.0)
Requires-Dist: grpcio-tools (>=1.59.3,<2.0.0)
Requires-Dist: jinja2 (>=3.1.2,<4.0.0)
Requires-Dist: protobuf (>=6.31.1,<7.0.0)
Requires-Dist: protobuf-to-pydantic[all] (>=0.3.3.1,<0.4.0.0)
Requires-Dist: pydantic[email] (>=2.5.2,<3.0.0)
